rangierapparat/__init__.py
rangierapparat/rangieren.py
rangierapparat/rangierlib/__init__.py
rangierapparat/rangierlib/ablauf.py
rangierapparat/rangierlib/ausparken.py
rangierapparat/rangierlib/circle_intersections.py
rangierapparat/rangierlib/fsolver.py
rangierapparat-0.0.6.dist-info/LICENSE
rangierapparat-0.0.6.dist-info/METADATA
rangierapparat-0.0.6.dist-info/WHEEL
rangierapparat-0.0.6.dist-info/top_level.txt
rangierapparat-0.0.6.dist-info/RECORD
