Metadata-Version: 2.1
Name: rangierapparat
Version: 0.0.6
Summary: A package to park your car.
Home-page: https://github.com/Frooob/rangierapparat
Author: Matthias Mildenberger
Author-email: regauf2@gmail.com
License: UNKNOWN
Project-URL: Bug Tracker, https://github.com/Frooob/rangierapparat/issues
Platform: UNKNOWN
Classifier: Programming Language :: Python :: 3
Classifier: License :: OSI Approved :: GNU General Public License v3 or later (GPLv3+)
Classifier: Operating System :: OS Independent
Requires-Python: >=3.6
License-File: LICENSE
